<annotation>
	<folder>train</folder>
	<filename>48957.jpg</filename>
	<path>Z:\weijun\DelftBikes\data\train\48957.jpg</path>
	<source>
		<database>Unknown</database>
	</source>
	<size>
		<width>640</width>
		<height>480</height>
		<depth>3</depth>
	</size>
	<segmented>0</segmented>
	<object>
		<name>back_hand_break@intact</name>
		<pose>Unspecified</pose>
		<truncated>0</truncated>
		<difficult>0</difficult>
		<bndbox>
			<xmin>242</xmin>
			<ymin>97</ymin>
			<xmax>271</xmax>
			<ymax>126</ymax>
		</bndbox>
	</object>
	<object>
		<name>back_handle@intact</name>
		<pose>Unspecified</pose>
		<truncated>0</truncated>
		<difficult>0</difficult>
		<bndbox>
			<xmin>261</xmin>
			<ymin>90</ymin>
			<xmax>296</xmax>
			<ymax>116</ymax>
		</bndbox>
	</object>
	<object>
		<name>front_handbreak@intact</name>
		<pose>Unspecified</pose>
		<truncated>0</truncated>
		<difficult>0</difficult>
		<bndbox>
			<xmin>166</xmin>
			<ymin>70</ymin>
			<xmax>186</xmax>
			<ymax>94</ymax>
		</bndbox>
	</object>
	<object>
		<name>front_handle@intact</name>
		<pose>Unspecified</pose>
		<truncated>0</truncated>
		<difficult>0</difficult>
		<bndbox>
			<xmin>167</xmin>
			<ymin>57</ymin>
			<xmax>188</xmax>
			<ymax>74</ymax>
		</bndbox>
	</object>
</annotation>
