<annotation>
	<folder>train</folder>
	<filename>F0153f-2016000120.jpg</filename>
	<path>Z:\weijun\DelftBikes\data\train\F0153f-2016000120.jpg</path>
	<source>
		<database>Unknown</database>
	</source>
	<size>
		<width>640</width>
		<height>427</height>
		<depth>3</depth>
	</size>
	<segmented>0</segmented>
	<object>
		<name>back_hand_break@intact</name>
		<pose>Unspecified</pose>
		<truncated>0</truncated>
		<difficult>0</difficult>
		<bndbox>
			<xmin>279</xmin>
			<ymin>66</ymin>
			<xmax>305</xmax>
			<ymax>96</ymax>
		</bndbox>
	</object>
	<object>
		<name>back_handle@intact</name>
		<pose>Unspecified</pose>
		<truncated>0</truncated>
		<difficult>0</difficult>
		<bndbox>
			<xmin>277</xmin>
			<ymin>53</ymin>
			<xmax>320</xmax>
			<ymax>76</ymax>
		</bndbox>
	</object>
	<object>
		<name>front_handbreak@intact</name>
		<pose>Unspecified</pose>
		<truncated>0</truncated>
		<difficult>0</difficult>
		<bndbox>
			<xmin>268</xmin>
			<ymin>33</ymin>
			<xmax>308</xmax>
			<ymax>72</ymax>
		</bndbox>
	</object>
	<object>
		<name>front_handle@intact</name>
		<pose>Unspecified</pose>
		<truncated>0</truncated>
		<difficult>0</difficult>
		<bndbox>
			<xmin>289</xmin>
			<ymin>24</ymin>
			<xmax>329</xmax>
			<ymax>45</ymax>
		</bndbox>
	</object>
</annotation>
