<annotation>
	<folder>train</folder>
	<filename>F0268a-2016000430.jpg</filename>
	<path>Z:\weijun\DelftBikes\data\train\F0268a-2016000430.jpg</path>
	<source>
		<database>Unknown</database>
	</source>
	<size>
		<width>352</width>
		<height>288</height>
		<depth>3</depth>
	</size>
	<segmented>0</segmented>
	<object>
		<name>back_handle@intact</name>
		<pose>Unspecified</pose>
		<truncated>0</truncated>
		<difficult>0</difficult>
		<bndbox>
			<xmin>157</xmin>
			<ymin>67</ymin>
			<xmax>174</xmax>
			<ymax>79</ymax>
		</bndbox>
	</object>
	<object>
		<name>front_handle@intact</name>
		<pose>Unspecified</pose>
		<truncated>0</truncated>
		<difficult>0</difficult>
		<bndbox>
			<xmin>105</xmin>
			<ymin>34</ymin>
			<xmax>126</xmax>
			<ymax>49</ymax>
		</bndbox>
	</object>
	<object>
		<name>ROI</name>
		<pose>Unspecified</pose>
		<truncated>0</truncated>
		<difficult>0</difficult>
		<bndbox>
			<xmin>7</xmin>
			<ymin>14</ymin>
			<xmax>330</xmax>
			<ymax>275</ymax>
		</bndbox>
	</object>
</annotation>
