<?xml version="1.0" encoding="utf-8"?>
<annotation>
    <filename>F0772f-2016000275.jpg</filename>
    <size>
        <width>640</width>
        <height>360</height>
        <depth>3</depth>
    </size>
    <imageid>5967</imageid>
    <object>
        <name>back_hand_break@occluded</name>
        <truncated>0</truncated>
        <difficult>0</difficult>
        <bndbox>
            <xmin>190</xmin>
            <ymin>105</ymin>
            <xmax>228</xmax>
            <ymax>144</ymax>
        </bndbox>
    <objectstate>3</objectstate>
    </object>
    <object>
        <name>back_handle@intact</name>
        <truncated>0</truncated>
        <difficult>0</difficult>
        <bndbox>
            <xmin>201</xmin>
            <ymin>102</ymin>
            <xmax>227</xmax>
            <ymax>125</ymax>
        </bndbox>
    <objectstate>0</objectstate>
    </object>
    <object>
        <name>front_handbreak@intact</name>
        <truncated>0</truncated>
        <difficult>0</difficult>
        <bndbox>
            <xmin>229</xmin>
            <ymin>155</ymin>
            <xmax>273</xmax>
            <ymax>178</ymax>
        </bndbox>
    <objectstate>0</objectstate>
    </object>
    <object>
        <name>front_handle@intact</name>
        <truncated>0</truncated>
        <difficult>0</difficult>
        <bndbox>
            <xmin>243</xmin>
            <ymin>143</ymin>
            <xmax>276</xmax>
            <ymax>162</ymax>
        </bndbox>
    <objectstate>0</objectstate>
    </object>
</annotation>