<?xml version="1.0" encoding="utf-8"?>
<annotation>
    <filename>F0772f-2016000800.jpg</filename>
    <size>
        <width>640</width>
        <height>360</height>
        <depth>3</depth>
    </size>
    <imageid>6193</imageid>
    <object>
        <name>back_hand_break@intact</name>
        <truncated>0</truncated>
        <difficult>0</difficult>
        <bndbox>
            <xmin>287</xmin>
            <ymin>103</ymin>
            <xmax>350</xmax>
            <ymax>136</ymax>
        </bndbox>
    <objectstate>0</objectstate>
    </object>
    <object>
        <name>back_handle@occluded</name>
        <truncated>0</truncated>
        <difficult>0</difficult>
        <bndbox>
            <xmin>285</xmin>
            <ymin>107</ymin>
            <xmax>313</xmax>
            <ymax>124</ymax>
        </bndbox>
    <objectstate>3</objectstate>
    </object>
    <object>
        <name>front_handbreak@intact</name>
        <truncated>0</truncated>
        <difficult>0</difficult>
        <bndbox>
            <xmin>256</xmin>
            <ymin>99</ymin>
            <xmax>347</xmax>
            <ymax>162</ymax>
        </bndbox>
    <objectstate>0</objectstate>
    </object>
    <object>
        <name>front_handle@intact</name>
        <truncated>0</truncated>
        <difficult>0</difficult>
        <bndbox>
            <xmin>300</xmin>
            <ymin>106</ymin>
            <xmax>338</xmax>
            <ymax>128</ymax>
        </bndbox>
    <objectstate>0</objectstate>
    </object>
</annotation>